{"type":"FeatureCollection","features":[{"type":"Feature","geometry":null,"properties":{"flowtype":"outflow","origin":"20023","counties":["8095:19","13257:21","20035:10","20057:5","20069:5","20129:36","20153:19","20193:10","31057:17","31063:9","37119:28","46047:1"]}},{"type":"Feature","geometry":null,"properties":{"flowtype":"inflow","origin":"20023","counties":["1097:2","8001:3","8031:2","8059:16","8069:23","8125:10","12049:20","20091:9","20149:1","20169:4","20181:13","20191:24","20199:22","20209:6","29037:3"]}}]}